hostseditor/__init__.py
hostseditor/editor.py
hostseditor/entry.py
hostseditor/utils.py
hosts_editor-1.0.0.dist-info/LICENSE
hosts_editor-1.0.0.dist-info/METADATA
hosts_editor-1.0.0.dist-info/WHEEL
hosts_editor-1.0.0.dist-info/top_level.txt
hosts_editor-1.0.0.dist-info/RECORD
