Metadata-Version: 2.1
Name: hosts-editor
Version: 1.0.0
Summary: A simple API for editing the hosts file.
Home-page: https://github.com/eitanwass/hosts_editor
Author: Ethan Wass
Author-email: eitanwass@gmail.com
License: MIT
Keywords: hosts file editing api
Platform: UNKNOWN
Classifier: Programming Language :: Python :: 3
Classifier: License :: OSI Approved :: MIT License
Classifier: Operating System :: Microsoft :: Windows
Classifier: Operating System :: POSIX :: Linux
Requires-Python: >=3.6
Requires-Dist: pytest
